Workbook

Sheet Read me
A1: Ridgeline GL export
A2: Pulled 16 Oct 2026 from the ledger. Calendar months, Oct 2025 through Sep 2026. Not a fiscal-year pack. Not a deck.
A4: Blue numbers are entered actuals. Black numbers are formulas. Do not paste a single month into a round-number slide.
A6: Tabs
A7: Monthly — one column per month
A8: Quarters — Q4 2025, Q1 2026, Q2 2026, Q3 2026, and the twelve-month total
A9: New bookers by source — does not tie to New bookers. The gap is the unattributed line.

Sheet Monthly
A1: Monthly actuals
A2: Entered figures are the close. Formulas are the relationships finance uses. Renewal rate is not on this tab.
A4: Line | B4: Oct 2025 | C4: Nov 2025 | D4: Dec 2025 | E4: Jan 2026 | F4: Feb 2026 | G4: Mar 2026 | H4: Apr 2026 | I4: May 2026 | J4: Jun 2026 | K4: Jul 2026 | L4: Aug 2026 | M4: Sep 2026 | N4: Twelve months
A5: Gross bookings | B5: 6200000 | C5: 14100000 | D5: 16100000 | E5: 15400000 | F5: 14200000 | G5: 12200000 | H5: 9800000 | I5: 5100000 | J5: 3700000 | K5: 2900000 | L5: 3400000 | M5: 4900000 | N5: =SUM(B5:M5)
A6: Cancellations | B6: 500000 | C6: 1600000 | D6: 2000000 | E6: 2100000 | F6: 1900000 | G6: 1600000 | H6: 1100000 | I6: 500000 | J6: 300000 | K6: 200000 | L6: 250000 | M6: 350000 | N6: =SUM(B6:M6)
A7: Net bookings | B7: =B5-B6 | C7: =C5-C6 | D7: =D5-D6 | E7: =E5-E6 | F7: =F5-F6 | G7: =G5-G6 | H7: =H5-H6 | I7: =I5-I6 | ... M7: =M5-M6 | N7: =SUM(B7:M7)
A8: Booking commission revenue | B8: 540000 | C8: 1220000 | D8: 1420000 | E8: 1380000 | F8: 1280000 | G8: 1060000 | H8: 820000 | I8: 430000 | J8: 300000 | K8: 240000 | L8: 290000 | M8: 410000 | N8: =SUM(B8:M8)
A9: Snow Pass revenue | B9: 160000 | C9: 170000 | D9: 190000 | E9: 200000 | F9: 210000 | G9: 200000 | H9: 200000 | I9: 190000 | J9: 190000 | K9: 200000 | L9: 210000 | M9: 230000 | N9: =SUM(B9:M9)
A10: Resort placement revenue | B10: 40000 | C10: 50000 | D10: 50000 | E10: 55000 | F10: 55000 | G10: 50000 | H10: 45000 | I10: 35000 | J10: 30000 | K10: 25000 | L10: 30000 | M10: 35000 | N10: =SUM(B10:M10)
A11: Net revenue | B11: =B8+B9+B10 | C11: =C8+C9+C10 | D11: =D8+D9+D10 | E11: =E8+E9+E10 | F11: =F8+F9+F10 | G11: =G8+G9+G10 | H11: =H8+H9+H10 | I11: =I8+I9+I10 | ... M11: =M8+M9+M10 | N11: =SUM(B11:M11)
A12: Affiliate fees, lodging | B12: 210000 | C12: 480000 | D12: 550000 | E12: 520000 | F12: 480000 | G12: 410000 | H12: 330000 | I12: 170000 | J12: 120000 | K12: 100000 | L12: 120000 | M12: 160000 | N12: =SUM(B12:M12)
A13: Payment fees | B13: 80000 | C13: 190000 | D13: 220000 | E13: 210000 | F13: 190000 | G13: 160000 | H13: 130000 | I13: 70000 | J13: 50000 | K13: 40000 | L13: 50000 | M13: 70000 | N13: =SUM(B13:M13)
A14: Snow, map, and forecast licenses | B14: 120000 | C14: 120000 | D14: 120000 | E14: 120000 | F14: 120000 | G14: 120000 | H14: 120000 | I14: 130000 | J14: 130000 | K14: 130000 | L14: 125000 | M14: 125000 | N14: =SUM(B14:M14)
A15: Support and chargebacks | B15: 80000 | C15: 150000 | D15: 180000 | E15: 220000 | F15: 210000 | G15: 190000 | H15: 140000 | I15: 80000 | J15: 60000 | K15: 50000 | L15: 60000 | M15: 80000 | N15: =SUM(B15:M15)
A16: Variable costs | B16: =B12+B13+B14+B15 | C16: =C12+C13+C14+C15 | D16: =D12+D13+D14+D15 | E16: =E12+E13+E14+E15 | F16: =F12+F13+F14+F15 | G16: =G12+G13+G14+G15 | H16: =H12+H13+H14+H15 | I16: =I12+I13+I14+I15 | ... M16: =M12+M13+M14+M15 | N16: =SUM(B16:M16)
A17: Contribution profit | B17: =B11-B16 | C17: =C11-C16 | D17: =D11-D16 | E17: =E11-E16 | F17: =F11-F16 | G17: =G11-G16 | H17: =H11-H16 | I17: =I11-I16 | ... M17: =M11-M16 | N17: =SUM(B17:M17)
A18: Contribution margin | B18: =IF(B11=0,"-",B17/B11) | C18: =IF(C11=0,"-",C17/C11) | D18: =IF(D11=0,"-",D17/D11) | E18: =IF(E11=0,"-",E17/E11) | F18: =IF(F11=0,"-",F17/F11) | G18: =IF(G11=0,"-",G17/G11) | H18: =IF(H11=0,"-",H17/H11) | I18: =IF(I11=0,"-",I17/I11) | ... N18: =IF(N11=0,"-",N17/N11)
A19: Sales and marketing | B19: 500000 | C19: 650000 | D19: 650000 | E19: 750000 | F19: 700000 | G19: 650000 | H19: 600000 | I19: 500000 | J19: 500000 | K19: 450000 | L19: 450000 | M19: 500000 | N19: =SUM(B19:M19)
A20: Product and engineering | B20: 700000 | C20: 750000 | D20: 750000 | E20: 760000 | F20: 770000 | G20: 770000 | H20: 800000 | I20: 820000 | J20: 830000 | K20: 820000 | L20: 840000 | M20: 840000 | N20: =SUM(B20:M20)
A21: G&A | B21: 280000 | C21: 300000 | D21: 320000 | E21: 310000 | F21: 310000 | G21: 320000 | H21: 340000 | I21: 380000 | J21: 380000 | K21: 360000 | L21: 380000 | M21: 380000 | N21: =SUM(B21:M21)
A22: Operating expenses | B22: =B19+B20+B21 | C22: =C19+C20+C21 | D22: =D19+D20+D21 | E22: =E19+E20+E21 | F22: =F19+F20+F21 | G22: =G19+G20+G21 | H22: =H19+H20+H21 | I22: =I19+I20+I21 | ... M22: =M19+M20+M21 | N22: =SUM(B22:M22)
A23: Operating income | B23: =B17-B22 | C23: =C17-C22 | D23: =D17-D22 | E23: =E17-E22 | F23: =F17-F22 | G23: =G17-G22 | H23: =H17-H22 | I23: =I17-I22 | ... M23: =M17-M22 | N23: =SUM(B23:M23)
A24: Cash, end of month | B24: 12400000 | C24: 11600000 | D24: 11200000 | E24: 10600000 | F24: 10100000 | G24: 9800000 | H24: 9400000 | I24: 15200000 | J24: 14100000 | K24: 15600000 | L24: 16000000 | M24: 16400000 | N24: =M24
A25: Headcount, end of month | B25: 72 | C25: 73 | D25: 74 | E25: 76 | F25: 78 | G25: 79 | H25: 81 | I25: 84 | J25: 86 | K25: 88 | L25: 90 | M25: 91 | N25: =M25
A26: Snow Pass subscribers, end of month | B26: 38200 | C26: 39800 | D26: 41200 | E26: 42600 | F26: 43900 | G26: 44800 | H26: 45600 | I26: 46400 | J26: 47100 | K26: 48900 | L26: 50600 | M26: 52300 | N26: =M26
A27: New bookers | B27: 4200 | C27: 6800 | D27: 7400 | E27: 7600 | F27: 7200 | G27: 6400 | H27: 3100 | I27: 2400 | J27: 2100 | K27: 1400 | L27: 1600 | M27: 1900 | N27: =SUM(B27:M27)
A28: Take rate (commission / gross bookings) | B28: =IF(B5=0,"-",B8/B5) | C28: =IF(C5=0,"-",C8/C5) | D28: =IF(D5=0,"-",D8/D5) | E28: =IF(E5=0,"-",E8/E5) | F28: =IF(F5=0,"-",F8/F5) | G28: =IF(G5=0,"-",G8/G5) | H28: =IF(H5=0,"-",H8/H5) | I28: =IF(I5=0,"-",I8/I5) | ... N28: =IF(N5=0,"-",N8/N5)

Sheet Quarters
A1: Calendar quarters
A2: Every figure on this tab is a formula back to Monthly, except renewal rate, which is entered once a quarter.
A4: Line | B4: Q4 2025 | C4: Q1 2026 | D4: Q2 2026 | E4: Q3 2026 | F4: Last twelve months
A5: =Monthly!A5 | B5: =SUM(Monthly!B5:D5) | C5: =SUM(Monthly!E5:G5) | D5: =SUM(Monthly!H5:J5) | E5: =SUM(Monthly!K5:M5) | F5: =SUM(B5:E5)
A6: =Monthly!A6 | B6: =SUM(Monthly!B6:D6) | C6: =SUM(Monthly!E6:G6) | D6: =SUM(Monthly!H6:J6) | E6: =SUM(Monthly!K6:M6) | F6: =SUM(B6:E6)
A7: =Monthly!A7 | B7: =SUM(Monthly!B7:D7) | C7: =SUM(Monthly!E7:G7) | D7: =SUM(Monthly!H7:J7) | E7: =SUM(Monthly!K7:M7) | F7: =SUM(B7:E7)
A8: =Monthly!A8 | B8: =SUM(Monthly!B8:D8) | C8: =SUM(Monthly!E8:G8) | D8: =SUM(Monthly!H8:J8) | E8: =SUM(Monthly!K8:M8) | F8: =SUM(B8:E8)
A9: =Monthly!A9 | B9: =SUM(Monthly!B9:D9) | C9: =SUM(Monthly!E9:G9) | D9: =SUM(Monthly!H9:J9) | E9: =SUM(Monthly!K9:M9) | F9: =SUM(B9:E9)
A10: =Monthly!A10 | B10: =SUM(Monthly!B10:D10) | C10: =SUM(Monthly!E10:G10) | D10: =SUM(Monthly!H10:J10) | E10: =SUM(Monthly!K10:M10) | F10: =SUM(B10:E10)
A11: =Monthly!A11 | B11: =SUM(Monthly!B11:D11) | C11: =SUM(Monthly!E11:G11) | D11: =SUM(Monthly!H11:J11) | E11: =SUM(Monthly!K11:M11) | F11: =SUM(B11:E11)
A12: =Monthly!A12 | B12: =SUM(Monthly!B12:D12) | C12: =SUM(Monthly!E12:G12) | D12: =SUM(Monthly!H12:J12) | E12: =SUM(Monthly!K12:M12) | F12: =SUM(B12:E12)
A13: =Monthly!A13 | B13: =SUM(Monthly!B13:D13) | C13: =SUM(Monthly!E13:G13) | D13: =SUM(Monthly!H13:J13) | E13: =SUM(Monthly!K13:M13) | F13: =SUM(B13:E13)
A14: =Monthly!A14 | B14: =SUM(Monthly!B14:D14) | C14: =SUM(Monthly!E14:G14) | D14: =SUM(Monthly!H14:J14) | E14: =SUM(Monthly!K14:M14) | F14: =SUM(B14:E14)
A15: =Monthly!A15 | B15: =SUM(Monthly!B15:D15) | C15: =SUM(Monthly!E15:G15) | D15: =SUM(Monthly!H15:J15) | E15: =SUM(Monthly!K15:M15) | F15: =SUM(B15:E15)
A16: =Monthly!A16 | B16: =SUM(Monthly!B16:D16) | C16: =SUM(Monthly!E16:G16) | D16: =SUM(Monthly!H16:J16) | E16: =SUM(Monthly!K16:M16) | F16: =SUM(B16:E16)
A17: =Monthly!A17 | B17: =SUM(Monthly!B17:D17) | C17: =SUM(Monthly!E17:G17) | D17: =SUM(Monthly!H17:J17) | E17: =SUM(Monthly!K17:M17) | F17: =SUM(B17:E17)
A18: =Monthly!A18 | B18: =IF(B11=0,"-",B17/B11) | C18: =IF(C11=0,"-",C17/C11) | D18: =IF(D11=0,"-",D17/D11) | E18: =IF(E11=0,"-",E17/E11) | F18: =IF(F11=0,"-",F17/F11)
A19: =Monthly!A19 | B19: =SUM(Monthly!B19:D19) | C19: =SUM(Monthly!E19:G19) | D19: =SUM(Monthly!H19:J19) | E19: =SUM(Monthly!K19:M19) | F19: =SUM(B19:E19)
A20: =Monthly!A20 | B20: =SUM(Monthly!B20:D20) | C20: =SUM(Monthly!E20:G20) | D20: =SUM(Monthly!H20:J20) | E20: =SUM(Monthly!K20:M20) | F20: =SUM(B20:E20)
A21: =Monthly!A21 | B21: =SUM(Monthly!B21:D21) | C21: =SUM(Monthly!E21:G21) | D21: =SUM(Monthly!H21:J21) | E21: =SUM(Monthly!K21:M21) | F21: =SUM(B21:E21)
A22: =Monthly!A22 | B22: =SUM(Monthly!B22:D22) | C22: =SUM(Monthly!E22:G22) | D22: =SUM(Monthly!H22:J22) | E22: =SUM(Monthly!K22:M22) | F22: =SUM(B22:E22)
A23: =Monthly!A23 | B23: =SUM(Monthly!B23:D23) | C23: =SUM(Monthly!E23:G23) | D23: =SUM(Monthly!H23:J23) | E23: =SUM(Monthly!K23:M23) | F23: =SUM(B23:E23)
A24: =Monthly!A24 | B24: =Monthly!D24 | C24: =Monthly!G24 | D24: =Monthly!J24 | E24: =Monthly!M24 | F24: =E24
A25: =Monthly!A25 | B25: =Monthly!D25 | C25: =Monthly!G25 | D25: =Monthly!J25 | E25: =Monthly!M25 | F25: =E25
A26: =Monthly!A26 | B26: =Monthly!D26 | C26: =Monthly!G26 | D26: =Monthly!J26 | E26: =Monthly!M26 | F26: =E26
A27: =Monthly!A27 | B27: =SUM(Monthly!B27:D27) | C27: =SUM(Monthly!E27:G27) | D27: =SUM(Monthly!H27:J27) | E27: =SUM(Monthly!K27:M27) | F27: =SUM(B27:E27)
A28: =Monthly!A28 | B28: =IF(B5=0,"-",B8/B5) | C28: =IF(C5=0,"-",C8/C5) | D28: =IF(D5=0,"-",D8/D5) | E28: =IF(E5=0,"-",E8/E5) | F28: =IF(F5=0,"-",F8/F5)
A30: Snow Pass renewal rate | B30: 0.71 | C30: 0.69 | D30: 0.76 | E30: 0.74 | F30: =E30

Sheet New bookers by source
A1: New bookers by source
A2: Warehouse attribution export, same pull. It does not cover every new booker. Unattributed is the plug.
A4: Source | B4: Oct 2025 | C4: Nov 2025 | D4: Dec 2025 | E4: Jan 2026 | F4: Feb 2026 | G4: Mar 2026 | H4: Apr 2026 | I4: May 2026 | J4: Jun 2026 | K4: Jul 2026 | L4: Aug 2026 | M4: Sep 2026 | N4: Twelve months
A5: Organic | B5: 1800 | C5: 2600 | D5: 2900 | E5: 3000 | F5: 2800 | G5: 2500 | H5: 1400 | I5: 1100 | J5: 900 | K5: 600 | L5: 700 | M5: 800 | N5: =SUM(B5:M5)
A6: Paid | B6: 1500 | C6: 2500 | D6: 2700 | E6: 2800 | F6: 2600 | G6: 2300 | H6: 900 | I6: 700 | J6: 600 | K6: 400 | L6: 450 | M6: 500 | N6: =SUM(B6:M6)
A7: Partner | B7: 400 | C7: 700 | D7: 800 | E7: 800 | F7: 750 | G7: 700 | H7: 300 | I7: 200 | J7: 200 | K7: 150 | L7: 150 | M7: 200 | N7: =SUM(B7:M7)
A8: Attributed | B8: =B5+B6+B7 | C8: =C5+C6+C7 | D8: =D5+D6+D7 | E8: =E5+E6+E7 | F8: =F5+F6+F7 | G8: =G5+G6+G7 | H8: =H5+H6+H7 | I8: =I5+I6+I7 | ... M8: =M5+M6+M7 | N8: =SUM(B8:M8)
A9: New bookers on the GL | B9: =Monthly!B27 | C9: =Monthly!C27 | D9: =Monthly!D27 | E9: =Monthly!E27 | F9: =Monthly!F27 | G9: =Monthly!G27 | H9: =Monthly!H27 | I9: =Monthly!I27 | ... M9: =Monthly!M27 | N9: =SUM(B9:M9)
A10: Unattributed | B10: =B9-B8 | C10: =C9-C8 | D10: =D9-D8 | E10: =E9-E8 | F10: =F9-F8 | G10: =G9-G8 | H10: =H9-H8 | I10: =I9-I8 | ... M10: =M9-M8 | N10: =SUM(B10:M10)
